pyBCS/__init__.py
pyBCS/dsp.py
pyBCS/light_transpose.py
pyBCS/scanpy2bcs.py
pyBCS/version.py
pyBCS_bioturing-0.4.10.dist-info/LICENSE
pyBCS_bioturing-0.4.10.dist-info/METADATA
pyBCS_bioturing-0.4.10.dist-info/WHEEL
pyBCS_bioturing-0.4.10.dist-info/top_level.txt
pyBCS_bioturing-0.4.10.dist-info/RECORD
