Metadata-Version: 2.1
Name: pyBCS-bioturing
Version: 0.4.10
Summary: Create BioTuring Compressed Study (bcs) file
Home-page: https://www.bioturing.com
Author: BioTuring
Author-email: support@bioturing.com
License: UNKNOWN
Platform: UNKNOWN
Classifier: Programming Language :: Python :: 3
Classifier: License :: OSI Approved :: MIT License
Classifier: Operating System :: OS Independent
Requires-Python: >=3.6
License-File: LICENSE
Requires-Dist: scanpy (>=1.6.0)
Requires-Dist: anndata (>=0.7.5)
Requires-Dist: loompy (>=3.0.6)
Requires-Dist: xmltodict (>=0.12.0)
Requires-Dist: imagecodecs (>=2022.2.22)
Requires-Dist: openpyxl (>=3.0.9)
Requires-Dist: xlrd (>=1.0.0)
Requires-Dist: opencv-python (>=4.5.5)
Requires-Dist: tifffile
